odoo/addons/account_partner_reconcile/README.rst
odoo/addons/account_partner_reconcile/__init__.py
odoo/addons/account_partner_reconcile/__manifest__.py
odoo/addons/account_partner_reconcile/i18n/account_partner_reconcile.pot
odoo/addons/account_partner_reconcile/i18n/da.po
odoo/addons/account_partner_reconcile/i18n/es.po
odoo/addons/account_partner_reconcile/i18n/es_AR.po
odoo/addons/account_partner_reconcile/i18n/fr.po
odoo/addons/account_partner_reconcile/i18n/fr_FR.po
odoo/addons/account_partner_reconcile/i18n/it.po
odoo/addons/account_partner_reconcile/i18n/pt.po
odoo/addons/account_partner_reconcile/models/__init__.py
odoo/addons/account_partner_reconcile/models/res_partner.py
odoo/addons/account_partner_reconcile/readme/CONFIGURE.md
odoo/addons/account_partner_reconcile/readme/CONTRIBUTORS.md
odoo/addons/account_partner_reconcile/readme/DESCRIPTION.md
odoo/addons/account_partner_reconcile/readme/USAGE.md
odoo/addons/account_partner_reconcile/static/description/icon.png
odoo/addons/account_partner_reconcile/static/description/index.html
odoo/addons/account_partner_reconcile/tests/__init__.py
odoo/addons/account_partner_reconcile/tests/test_account_partner_reconcile.py
odoo/addons/account_partner_reconcile/views/res_partner_view.xml
odoo_addon_account_partner_reconcile-17.0.1.0.0.2.dist-info/METADATA
odoo_addon_account_partner_reconcile-17.0.1.0.0.2.dist-info/WHEEL
odoo_addon_account_partner_reconcile-17.0.1.0.0.2.dist-info/top_level.txt
odoo_addon_account_partner_reconcile-17.0.1.0.0.2.dist-info/RECORD
